iVAE/__init__.py
iVAE/agent.py
iVAE/cli.py
iVAE/environment.py
iVAE/mixin.py
iVAE/model.py
iVAE/module.py
iVAE/utils.py
iVAE-0.0.5.dist-info/LICENSE
iVAE-0.0.5.dist-info/METADATA
iVAE-0.0.5.dist-info/WHEEL
iVAE-0.0.5.dist-info/entry_points.txt
iVAE-0.0.5.dist-info/top_level.txt
iVAE-0.0.5.dist-info/RECORD
