Metadata-Version: 2.1
Name: iVAE
Version: 0.0.5
Summary: Interpretable Variational Autoencoder for Single-Cell Data
Home-page: https://github.com/PeterPonyu/iVAE
Author: Zeyu Fu
Author-email: fuzeyu99@126.com
License: MIT
Platform: UNKNOWN
Classifier: License :: OSI Approved :: MIT License
Classifier: Development Status :: 3 - Alpha
Classifier: Programming Language :: Python :: 3
Classifier: Intended Audience :: Science/Research
Classifier: Topic :: Scientific/Engineering :: Bio-Informatics
Requires-Python: >=3.9
License-File: LICENSE
Requires-Dist: scanpy >=1.10.4
Requires-Dist: scib >=1.1.5
Requires-Dist: torch >=1.13.1
Requires-Dist: joblib >=1.2.0
Requires-Dist: tqdm >=4.64.1
